[
    {
        "name": "Avatar",
        "type": "movie",
        "thumbnail": "https://example.com/avatar.jpg",
        "links": {
            "480p": "http://example.com/avatar-480p.mp4",
            "720p": "http://example.com/avatar-720p.mp4",
            "1080p": "http://example.com/avatar-1080p.mp4"
        }
    },
    {
        "name": "Raid 2",
        "type": "movie",
        "thumbnail": "https://img.nowrunning.com/content/movie/2024/raid-29076/bg-video48202552747.jpg",
        "links": {
            "480p": "https://vcloud.lol/qqqoz4opy1gaq01",
            "720p": "https://vcloud.lol/exm7sbm5ieix1sz",
            "1080p": "https://vcloud.lol/d1ooqesd6sgevdv",
            "2K": "https://vcloud.lol/36sdsfhd9_u61an"
        }
    },
    {
        "name": "Stranger Things",
        "type": "webseries",
        "thumbnail": "https://static1.cbrimages.com/wordpress/wp-content/uploads/2023/04/stranger-things-cartoon.jpg",
        "episodes": {
            "S01E01": {
                "480p": "http://example.com/st-101-480p.mp4",
                "720p": "http://example.com/st-101-720p.mp4"
            },
            "S01E02": {
                "480p": "http://example.com/st-102-480p.mp4",
                "720p": "http://example.com/st-102-720p.mp4"
            }
        }
    },
    {
        "name": "Naruto",
        "type": "anime",
        "thumbnail": "https://example.com/naruto.jpg",
        "episodes": {
            "Episode 1": {
                "480p": "http://example.com/naruto-ep1-480p.mp4",
                "720p": "http://example.com/naruto-ep1-720p.mp4"
            },
            "Episode 2": {
                "480p": "http://example.com/naruto-ep2-480p.mp4"
            }
        }
    }
]



